{
"meta":{"test_sets":[],"test_metrics":[],"learn_metrics":[{"best_value":"Min","name":"RMSE"}],"launch_mode":"Train","parameters":"","iteration_count":100,"learn_sets":["learn"],"name":"experiment"},
"iterations":[
{"learn":[5696.582998],"iteration":0,"passed_time":0.05257261716,"remaining_time":5.204689099},
{"learn":[4905.508048],"iteration":1,"passed_time":0.05622520145,"remaining_time":2.755034871},
{"learn":[4424.727937],"iteration":2,"passed_time":0.06056436119,"remaining_time":1.958247678},
{"learn":[4192.042063],"iteration":3,"passed_time":0.06274739212,"remaining_time":1.505937411},
{"learn":[4035.245552],"iteration":4,"passed_time":0.06509455404,"remaining_time":1.236796527},
{"learn":[3928.290415],"iteration":5,"passed_time":0.06847643344,"remaining_time":1.072797457},
{"learn":[3856.149958],"iteration":6,"passed_time":0.07074374993,"remaining_time":0.9398812491},
{"learn":[3819.33023],"iteration":7,"passed_time":0.07302620548,"remaining_time":0.8398013631},
{"learn":[3788.774744],"iteration":8,"passed_time":0.07521612345,"remaining_time":0.7605185816},
{"learn":[3758.591573],"iteration":9,"passed_time":0.0775748435,"remaining_time":0.6981735915},
{"learn":[3742.312388],"iteration":10,"passed_time":0.0798019592,"remaining_time":0.6456703972},
{"learn":[3729.678896],"iteration":11,"passed_time":0.08192451853,"remaining_time":0.6007798026},
{"learn":[3701.689126],"iteration":12,"passed_time":0.08428757712,"remaining_time":0.5640784007},
{"learn":[3687.438411],"iteration":13,"passed_time":0.08650082323,"remaining_time":0.5313621998},
{"learn":[3670.683853],"iteration":14,"passed_time":0.08931248437,"remaining_time":0.5061040781},
{"learn":[3657.966192],"iteration":15,"passed_time":0.09151000964,"remaining_time":0.4804275506},
{"learn":[3640.699716],"iteration":16,"passed_time":0.09367754854,"remaining_time":0.4573668546},
{"learn":[3606.745969],"iteration":17,"passed_time":0.0958550279,"remaining_time":0.4366729049},
{"learn":[3586.488441],"iteration":18,"passed_time":0.1044582547,"remaining_time":0.4453220331},
{"learn":[3568.098348],"iteration":19,"passed_time":0.1067664232,"remaining_time":0.4270656927},
{"learn":[3557.939671],"iteration":20,"passed_time":0.1090809452,"remaining_time":0.410352127},
{"learn":[3539.212397],"iteration":21,"passed_time":0.1114657216,"remaining_time":0.3951966493},
{"learn":[3524.580062],"iteration":22,"passed_time":0.113897915,"remaining_time":0.3813104109},
{"learn":[3509.616977],"iteration":23,"passed_time":0.1161992038,"remaining_time":0.3679641454},
{"learn":[3489.514884],"iteration":24,"passed_time":0.1191628613,"remaining_time":0.3574885838},
{"learn":[3475.93509],"iteration":25,"passed_time":0.1219254974,"remaining_time":0.3470187233},
{"learn":[3462.163617],"iteration":26,"passed_time":0.1242167884,"remaining_time":0.335845391},
{"learn":[3450.78583],"iteration":27,"passed_time":0.1269125504,"remaining_time":0.3263465583},
{"learn":[3432.257637],"iteration":28,"passed_time":0.1292399543,"remaining_time":0.3164150605},
{"learn":[3413.842649],"iteration":29,"passed_time":0.1313442677,"remaining_time":0.3064699581},
{"learn":[3390.222275],"iteration":30,"passed_time":0.1507635528,"remaining_time":0.3355704884},
{"learn":[3376.666708],"iteration":31,"passed_time":0.1671617939,"remaining_time":0.355218812},
{"learn":[3366.297264],"iteration":32,"passed_time":0.1716303273,"remaining_time":0.3484615735},
{"learn":[3350.661515],"iteration":33,"passed_time":0.1818437496,"remaining_time":0.352990808},
{"learn":[3344.877281],"iteration":34,"passed_time":0.1844333015,"remaining_time":0.3425189885},
{"learn":[3325.3539],"iteration":35,"passed_time":0.1871176638,"remaining_time":0.3326536246},
{"learn":[3317.077342],"iteration":36,"passed_time":0.18943293,"remaining_time":0.3225479618},
{"learn":[3307.155523],"iteration":37,"passed_time":0.1917466305,"remaining_time":0.3128497656},
{"learn":[3298.565697],"iteration":38,"passed_time":0.1940289128,"remaining_time":0.3034811201},
{"learn":[3291.624622],"iteration":39,"passed_time":0.1965445,"remaining_time":0.29481675},
{"learn":[3279.874557],"iteration":40,"passed_time":0.1990021567,"remaining_time":0.2863689572},
{"learn":[3271.021171],"iteration":41,"passed_time":0.2013325914,"remaining_time":0.2780307214},
{"learn":[3260.250855],"iteration":42,"passed_time":0.2036905664,"remaining_time":0.2700084253},
{"learn":[3242.634586],"iteration":43,"passed_time":0.2059589271,"remaining_time":0.2621295435},
{"learn":[3230.841714],"iteration":44,"passed_time":0.2082906773,"remaining_time":0.2545774944},
{"learn":[3226.020697],"iteration":45,"passed_time":0.2147312399,"remaining_time":0.2520758033},
{"learn":[3223.367742],"iteration":46,"passed_time":0.2171971707,"remaining_time":0.2449244691},
{"learn":[3216.395395],"iteration":47,"passed_time":0.2198170685,"remaining_time":0.2381351575},
{"learn":[3212.188949],"iteration":48,"passed_time":0.2221862101,"remaining_time":0.231255035},
{"learn":[3194.737604],"iteration":49,"passed_time":0.2247225768,"remaining_time":0.2247225768},
{"learn":[3187.590552],"iteration":50,"passed_time":0.2270402999,"remaining_time":0.2181367587},
{"learn":[3176.386451],"iteration":51,"passed_time":0.2300096604,"remaining_time":0.2123166096},
{"learn":[3166.043926],"iteration":52,"passed_time":0.2323719366,"remaining_time":0.2060656797},
{"learn":[3151.817647],"iteration":53,"passed_time":0.2495615175,"remaining_time":0.2125894408},
{"learn":[3147.144054],"iteration":54,"passed_time":0.2521951099,"remaining_time":0.2063414536},
{"learn":[3138.241311],"iteration":55,"passed_time":0.2544266471,"remaining_time":0.1999066513},
{"learn":[3136.724919],"iteration":56,"passed_time":0.2567255116,"remaining_time":0.1936701228},
{"learn":[3132.88058],"iteration":57,"passed_time":0.2590416417,"remaining_time":0.1875818785},
{"learn":[3127.54026],"iteration":58,"passed_time":0.261372316,"remaining_time":0.1816316095},
{"learn":[3116.009058],"iteration":59,"passed_time":0.2642582706,"remaining_time":0.1761721804},
{"learn":[3113.212168],"iteration":60,"passed_time":0.2666334591,"remaining_time":0.1704705722},
{"learn":[3110.870289],"iteration":61,"passed_time":0.2691493189,"remaining_time":0.1649624858},
{"learn":[3105.614654],"iteration":62,"passed_time":0.2715695504,"remaining_time":0.159493228},
{"learn":[3102.730544],"iteration":63,"passed_time":0.2738070859,"remaining_time":0.1540164858},
{"learn":[3094.806873],"iteration":64,"passed_time":0.2760771085,"remaining_time":0.1486569046},
{"learn":[3081.234433],"iteration":65,"passed_time":0.2784302709,"remaining_time":0.1434337759},
{"learn":[3075.097383],"iteration":66,"passed_time":0.2808787525,"remaining_time":0.1383432662},
{"learn":[3071.512333],"iteration":67,"passed_time":0.2829732575,"remaining_time":0.1331638859},
{"learn":[3061.472992],"iteration":68,"passed_time":0.2853321434,"remaining_time":0.1281927021},
{"learn":[3051.787142],"iteration":69,"passed_time":0.287435961,"remaining_time":0.1231868404},
{"learn":[3042.580248],"iteration":70,"passed_time":0.2895863845,"remaining_time":0.1182817627},
{"learn":[3040.503438],"iteration":71,"passed_time":0.2917645247,"remaining_time":0.1134639818},
{"learn":[3031.21127],"iteration":72,"passed_time":0.2951740252,"remaining_time":0.1091739545},
{"learn":[3019.274716],"iteration":73,"passed_time":0.2978502553,"remaining_time":0.1046500897},
{"learn":[3008.236147],"iteration":74,"passed_time":0.310934722,"remaining_time":0.1036449073},
{"learn":[2998.243363],"iteration":75,"passed_time":0.3137131618,"remaining_time":0.09906731426},
{"learn":[2993.247456],"iteration":76,"passed_time":0.3159025605,"remaining_time":0.09436050509},
{"learn":[2988.619737],"iteration":77,"passed_time":0.3183439954,"remaining_time":0.08978933203},
{"learn":[2981.483988],"iteration":78,"passed_time":0.3206845268,"remaining_time":0.08524525397},
{"learn":[2971.387899],"iteration":79,"passed_time":0.323006822,"remaining_time":0.08075170549},
{"learn":[2970.095763],"iteration":80,"passed_time":0.3254333843,"remaining_time":0.07633622595},
{"learn":[2964.362147],"iteration":81,"passed_time":0.3481198756,"remaining_time":0.07641655807},
{"learn":[2950.91334],"iteration":82,"passed_time":0.3508017185,"remaining_time":0.0718509544},
{"learn":[2943.524465],"iteration":83,"passed_time":0.3530833913,"remaining_time":0.0672539793},
{"learn":[2940.54858],"iteration":84,"passed_time":0.3553618609,"remaining_time":0.06271091662},
{"learn":[2938.06376],"iteration":85,"passed_time":0.3576755553,"remaining_time":0.05822625319},
{"learn":[2931.316339],"iteration":86,"passed_time":0.3599823285,"remaining_time":0.05379046287},
{"learn":[2919.659596],"iteration":87,"passed_time":0.3631481751,"remaining_time":0.0495202057},
{"learn":[2912.922719],"iteration":88,"passed_time":0.3666633113,"remaining_time":0.04531793735},
{"learn":[2903.559934],"iteration":89,"passed_time":0.3768657395,"remaining_time":0.04187397105},
{"learn":[2902.265553],"iteration":90,"passed_time":0.3790257023,"remaining_time":0.03748605847},
{"learn":[2901.300191],"iteration":91,"passed_time":0.3828821538,"remaining_time":0.03329410033},
{"learn":[2895.929344],"iteration":92,"passed_time":0.389264611,"remaining_time":0.02929948685},
{"learn":[2894.703467],"iteration":93,"passed_time":0.3916223676,"remaining_time":0.0249971724},
{"learn":[2885.034158],"iteration":94,"passed_time":0.3942153173,"remaining_time":0.02074817459},
{"learn":[2882.967836],"iteration":95,"passed_time":0.3962389105,"remaining_time":0.0165099546},
{"learn":[2870.071911],"iteration":96,"passed_time":0.3987427085,"remaining_time":0.01233224872},
{"learn":[2863.153851],"iteration":97,"passed_time":0.4016720988,"remaining_time":0.008197389771},
{"learn":[2856.895927],"iteration":98,"passed_time":0.4167171446,"remaining_time":0.004209264087},
{"learn":[2853.956621],"iteration":99,"passed_time":0.4312342617,"remaining_time":0}
]}